pexicdb/__about__.py
pexicdb/__init__.py
pexicdb/core.py
pexicdb/fields.py
pexicdb/functions.py
pexicdb/helpers.py
pexicdb/lock.py
pexicdb-0.0.1.dist-info/METADATA
pexicdb-0.0.1.dist-info/WHEEL
pexicdb-0.0.1.dist-info/top_level.txt
pexicdb-0.0.1.dist-info/RECORD
