Metadata-Version: 2.1
Name: pexicdb
Version: 0.0.1
Summary: Pexicdb is a simple model based file database
Home-page: https://github.com/hakiKhuva/pexicdb
Author: Harkishan Khuva
Author-email: harkishankhuva02@gmail.com
License: MIT
Platform: UNKNOWN
Classifier: Programming Language :: Python :: 3
Classifier: License :: OSI Approved :: MIT License
Classifier: Intended Audience :: Developers
Classifier: Environment :: Console
Requires-Python: >=3.10
